naive/naive.py
naiveb1-0.0.1.dist-info/LICENSE
naiveb1-0.0.1.dist-info/METADATA
naiveb1-0.0.1.dist-info/WHEEL
naiveb1-0.0.1.dist-info/top_level.txt
naiveb1-0.0.1.dist-info/RECORD
