Metadata-Version: 2.1
Name: naiveb1
Version: 0.0.1
Summary: This is for simplex method
Author-email: Vikneesh <vickyvikneesh6@gmail.com>
Classifier: Programming Language :: Python :: 3
Classifier: License :: OSI Approved :: MIT License
Classifier: Operating System :: OS Independent
Requires-Python: >=3.7
License-File: LICENSE
